cvttf_NotoSansCJK_Light/NotoSansCJKtc-Light.otf
cvttf_NotoSansCJK_Light/__init__.py
cvttf_NotoSansCJK_Light-1.0.data/data/NotoSansCJKtc-Light.otf
cvttf_NotoSansCJK_Light-1.0.dist-info/DESCRIPTION.rst
cvttf_NotoSansCJK_Light-1.0.dist-info/METADATA
cvttf_NotoSansCJK_Light-1.0.dist-info/RECORD
cvttf_NotoSansCJK_Light-1.0.dist-info/WHEEL
cvttf_NotoSansCJK_Light-1.0.dist-info/metadata.json
cvttf_NotoSansCJK_Light-1.0.dist-info/top_level.txt
