Metadata-Version: 2.0
Name: cvttf-NotoSansCJK-Light
Version: 1.0
Summary: Font file for CVTTF
Home-page: https://github.com/issaclin32/CVTTF
Author: Issac Lin
Author-email: issaclin32@gmail.com
License: UNKNOWN
Platform: UNKNOWN
Classifier: Programming Language :: Python :: 3
Classifier: License :: OSI Approved :: MIT License
Classifier: Operating System :: OS Independent
